pylablib/__init__.py
pylablib/__main__.py
pylablib/aux_libs.py
pylablib/widgets.py
pylablib/core/__init__.py
pylablib/core/dataproc/__export__.py
pylablib/core/dataproc/__init__.py
pylablib/core/dataproc/callable.py
pylablib/core/dataproc/ctransform.cp310-win32.pyd
pylablib/core/dataproc/ctransform_fallback.py
pylablib/core/dataproc/feature.py
pylablib/core/dataproc/filters.py
pylablib/core/dataproc/fitting.py
pylablib/core/dataproc/fourier.py
pylablib/core/dataproc/iir_transform.py
pylablib/core/dataproc/image.py
pylablib/core/dataproc/interpolate.py
pylablib/core/dataproc/specfunc.py
pylablib/core/dataproc/table_wrap.py
pylablib/core/dataproc/transform.py
pylablib/core/dataproc/utils.py
pylablib/core/devio/SCPI.py
pylablib/core/devio/__export__.py
pylablib/core/devio/__init__.py
pylablib/core/devio/backend_logger.py
pylablib/core/devio/base.py
pylablib/core/devio/comm_backend.py
pylablib/core/devio/data_format.py
pylablib/core/devio/hid.py
pylablib/core/devio/hid_base.py
pylablib/core/devio/hid_lib.py
pylablib/core/devio/interface.py
pylablib/core/fileio/__export__.py
pylablib/core/fileio/__init__.py
pylablib/core/fileio/bin_transform.py
pylablib/core/fileio/datafile.py
pylablib/core/fileio/dict_entry.py
pylablib/core/fileio/loadfile.py
pylablib/core/fileio/loadfile_utils.py
pylablib/core/fileio/location.py
pylablib/core/fileio/parse_csv.py
pylablib/core/fileio/savefile.py
pylablib/core/fileio/table_stream.py
pylablib/core/gui/__export__.py
pylablib/core/gui/__init__.py
pylablib/core/gui/formatter.py
pylablib/core/gui/limiter.py
pylablib/core/gui/utils.py
pylablib/core/gui/value_handling.py
pylablib/core/gui/widgets/__export__.py
pylablib/core/gui/widgets/__init__.py
pylablib/core/gui/widgets/button.py
pylablib/core/gui/widgets/button_selector.py
pylablib/core/gui/widgets/combo_box.py
pylablib/core/gui/widgets/container.py
pylablib/core/gui/widgets/edit.py
pylablib/core/gui/widgets/label.py
pylablib/core/gui/widgets/layout_manager.py
pylablib-1.4.4.dist-info/licenses/LICENSE
pylablib-1.4.4.dist-info/METADATA
pylablib-1.4.4.dist-info/WHEEL
pylablib-1.4.4.dist-info/top_level.txt
pylablib-1.4.4.dist-info/RECORD
