Metadata-Version: 2.1
Name: pylablib
Version: 1.4.4
Summary: Code for use in lab environment: experiment automation, data acquisition, device communication
Home-page: https://github.com/AlexShkarin/pyLabLib
Author: Alexey Shkarin
Author-email: pylablib@gmail.com
License: GPLv3
Project-URL: Documentation, https://pylablib.readthedocs.io
Project-URL: Source, https://github.com/AlexShkarin/pyLabLib/
Project-URL: Tracker, https://github.com/AlexShkarin/pyLabLib/issues
Classifier: Development Status :: 4 - Beta
Classifier: Operating System :: Microsoft :: Windows
Classifier: Intended Audience :: Developers
Classifier: Intended Audience :: Science/Research
Classifier: Topic :: Scientific/Engineering
Classifier: License :: OSI Approved :: GNU General Public License v3 (GPLv3)
Classifier: Programming Language :: Python :: 3
Classifier: Programming Language :: Python :: 3.6
Classifier: Programming Language :: Python :: 3.7
Classifier: Programming Language :: Python :: 3.8
Classifier: Programming Language :: Python :: 3.9
Classifier: Programming Language :: Python :: 3.10
Classifier: Programming Language :: Python :: 3.11
Classifier: Programming Language :: Python :: 3.12
Classifier: Programming Language :: Python :: 3.13
License-File: LICENSE
Requires-Dist: numpy
Requires-Dist: scipy
Requires-Dist: pandas
Requires-Dist: rpyc
Requires-Dist: numba
Requires-Dist: pyft232
Requires-Dist: pyvisa>=1.6
Requires-Dist: pyserial
Requires-Dist: pyusb
Requires-Dist: pyqt5>=5.9
Requires-Dist: pyqtgraph
Provides-Extra: devio-full
Requires-Dist: nidaqmx; extra == "devio-full"
Requires-Dist: websocket-client; extra == "devio-full"
